MANIFEST.in
setup.py
plutonium_plugin_output_transmission/__init__.py
plutonium_plugin_output_transmission/plugin_config.py
plutonium_plugin_output_transmission.egg-info/PKG-INFO
plutonium_plugin_output_transmission.egg-info/SOURCES.txt
plutonium_plugin_output_transmission.egg-info/dependency_links.txt
plutonium_plugin_output_transmission.egg-info/requires.txt
plutonium_plugin_output_transmission.egg-info/top_level.txt