Metadata-Version: 1.0
Name: plutonium-plugin-output-transmission
Version: 1.0.1
Summary: Transmission output plugin for Plutonium
Home-page: https://github.com/voidpp/plutonium-plugin-output-transmission
Author: Lajos Santa
Author-email: santa.lajos@coldline.hu
License: MIT
Platform: UNKNOWN
